{
    "IIT_Kanpur-Virtual_Combustion_and_Atomization_Laboratory.jpg": {
        "contentType": "image/jpeg", 
        "content_son": {
            "category": "asset", 
            "course": "mech48", 
            "name": "IIT_Kanpur-Virtual_Combustion_and_Atomization_Laboratory.jpg", 
            "org": "Virtual-Labs", 
            "revision": null, 
            "run": "Anytime", 
            "tag": "c4x"
        }, 
        "displayname": "IIT Kanpur-Virtual Combustion and Atomization Laboratory.jpg", 
        "filename": "asset-v1:Virtual-Labs+mech48+Anytime+type@asset+block@IIT_Kanpur-Virtual_Combustion_and_Atomization_Laboratory.jpg", 
        "import_path": "IIT Kanpur-Virtual Combustion and Atomization Laboratory.jpg", 
        "locked": false, 
        "thumbnail_location": [
            "c4x", 
            "Virtual-Labs", 
            "mech48", 
            "thumbnail", 
            "IIT_Kanpur-Virtual_Combustion_and_Atomization_Laboratory.jpg", 
            null
        ]
    }
}